adalasso/__init__.py
adalasso/_adaptive_lasso.py
adalasso/adalasso_path.py
adalasso/tests/__init__.py
adalasso/tests/test_adaptive_lasso.py
adalasso-0.1.1.dist-info/licenses/LICENSE
adalasso-0.1.1.dist-info/METADATA
adalasso-0.1.1.dist-info/WHEEL
adalasso-0.1.1.dist-info/top_level.txt
adalasso-0.1.1.dist-info/RECORD
