Metadata-Version: 2.4
Name: adalasso
Version: 0.1.1
Summary: Adaptive Lasso implementation following scikit-learn API
Home-page: https://github.com/ErikHartman/adalasso
Author: Erik Hartman
Author-email: erik.hartman@hotmail.com
Classifier: Programming Language :: Python :: 3
Classifier: License :: OSI Approved :: MIT License
Classifier: Intended Audience :: Science/Research
Classifier: Topic :: Scientific/Engineering
Requires-Python: >=3.6
License-File: LICENSE
Requires-Dist: numpy>=1.16.0
Requires-Dist: scikit-learn>=0.24.0
Requires-Dist: matplotlib>=3.0.0
Dynamic: author
Dynamic: author-email
Dynamic: classifier
Dynamic: description
Dynamic: description-content-type
Dynamic: home-page
Dynamic: license-file
Dynamic: requires-dist
Dynamic: requires-python
Dynamic: summary
